{
  "gate": "GATE-06",
  "phase": "06-implementation",
  "artifact_folder": "REQ-0095-impact-analysis-team-port",
  "requirements": ["REQ-0095", "REQ-0096", "REQ-0097", "REQ-0126"],
  "timestamp": "2026-03-22T18:35:00.000Z",
  "checklist": {
    "all_features_implemented": true,
    "unit_test_coverage_80_plus": true,
    "all_tests_passing": true,
    "code_follows_linting_standards": true,
    "implementation_matches_design": true,
    "code_documentation_complete": true
  },
  "test_summary": {
    "new_tests": 62,
    "core_suite_total": 537,
    "core_suite_passing": 537,
    "core_suite_failing": 0,
    "regressions": 0,
    "test_files_created": [
      "tests/core/teams/instances.test.js",
      "tests/core/teams/instance-registry.test.js",
      "tests/core/teams/bridge-team-instances.test.js",
      "tests/core/skills/injection-planner.test.js",
      "tests/core/skills/bridge-skill-planner.test.js"
    ]
  },
  "production_files_created": [
    "src/core/teams/instances/impact-analysis.js",
    "src/core/teams/instances/tracing.js",
    "src/core/teams/instances/quality-loop.js",
    "src/core/teams/instance-registry.js",
    "src/core/skills/injection-planner.js",
    "src/core/bridge/team-instances.cjs",
    "src/core/bridge/skill-planner.cjs"
  ],
  "constitutional_compliance": {
    "articles_validated": [
      "Article I: Specification Primacy",
      "Article II: Test-First Development",
      "Article III: Security by Design",
      "Article V: Simplicity First",
      "Article VII: Artifact Traceability",
      "Article VIII: Documentation Currency",
      "Article IX: Quality Gate Integrity",
      "Article X: Fail-Safe Defaults",
      "Article XIII: Module System Consistency"
    ],
    "status": "compliant",
    "violations": []
  },
  "iterations": {
    "test_iterations": 1,
    "constitutional_iterations": 1,
    "total_iterations": 1
  },
  "verdict": "PASS"
}
