{
  "gate": "GATE-08",
  "phase": "08-code-review",
  "workflow": "REQ-0032-issue-tracker-integration-during-installation",
  "result": "PASS",
  "timestamp": "2026-02-22T00:00:00Z",
  "reviewer": "QA Engineer (Phase 08)",
  "checklist": {
    "code_review_completed": true,
    "no_critical_issues_open": true,
    "static_analysis_passing": true,
    "code_coverage_meets_thresholds": true,
    "coding_standards_followed": true,
    "performance_acceptable": true,
    "security_review_complete": true,
    "qa_signoff_obtained": true
  },
  "metrics": {
    "files_reviewed": 8,
    "feature_tests_passing": "39/39",
    "full_suite_esm": "649/653",
    "full_suite_cjs": "2396/2398",
    "pre_existing_failures": 6,
    "new_regressions": 0,
    "critical_findings": 0,
    "major_findings": 0,
    "minor_findings": 0,
    "informational_findings": 2,
    "new_code_path_coverage": "100%",
    "npm_audit_vulnerabilities": 0
  },
  "constitutional_compliance": {
    "article_II_test_first": "PASS",
    "article_V_simplicity": "PASS",
    "article_VI_code_review": "PASS",
    "article_VII_traceability": "PASS",
    "article_IX_quality_gate": "PASS"
  },
  "artifacts": [
    "docs/quality/REQ-0032-issue-tracker-integration-during-installation/code-review.md"
  ],
  "phase_timing": {
    "debate_rounds_used": 0,
    "fan_out_chunks": 0
  }
}
