{
  "gate": "GATE-06",
  "phase": "06-implementation",
  "requirement": "REQ-0014",
  "feature": "BACKLOG.md Scaffolding",
  "validated_at": "2026-02-14T18:00:00.000Z",
  "status": "passed",
  "checklist": {
    "all_features_implemented": true,
    "unit_test_coverage_80_percent": true,
    "all_tests_passing": true,
    "code_follows_linting_standards": true,
    "implementation_matches_design": true,
    "code_documentation_complete": true
  },
  "test_results": {
    "new_installer_tests": 15,
    "new_uninstaller_tests": 3,
    "total_new_tests": 18,
    "new_tests_passing": 18,
    "new_tests_failing": 0,
    "full_suite": {
      "esm_total": 599,
      "esm_pass": 598,
      "esm_fail": 1,
      "esm_pre_existing_failures": ["TC-E09 (README agent count - unrelated)"],
      "cjs_total": 1280,
      "cjs_pass": 1280,
      "cjs_fail": 0,
      "regressions": 0
    }
  },
  "files_modified": [
    "lib/installer.js",
    "lib/installer.test.js",
    "lib/uninstaller.test.js"
  ],
  "files_not_modified": [
    "lib/uninstaller.js"
  ],
  "files_created": [
    "docs/requirements/REQ-0014-backlog-scaffolding/implementation-notes.md"
  ],
  "ac_coverage": {
    "total": 12,
    "covered": 12,
    "percentage": 100
  },
  "constitutional_compliance": {
    "article_I_specification_primacy": "PASS - Code implements module-design.md exactly",
    "article_II_test_first": "PASS - 18 tests written before production code (TDD Red-Green verified)",
    "article_III_security_by_design": "PASS - No security concerns (file scaffolding only)",
    "article_V_simplicity_first": "PASS - ~20 lines of production code, zero new dependencies",
    "article_VII_artifact_traceability": "PASS - REQ-0014 referenced in code comments and test names",
    "article_VIII_documentation_currency": "PASS - JSDoc and inline documentation complete",
    "article_IX_quality_gate_integrity": "PASS - All required artifacts exist, all tests pass",
    "article_X_fail_safe_defaults": "PASS - Exists-check guard, dry-run guard, no silent failures"
  }
}
